gpt.py
core/__init__.py
core/commands.py
core/config.py
core/memory.py
konijima_gpt_cli-1.1.2.dist-info/licenses/LICENSE
konijima_gpt_cli-1.1.2.dist-info/METADATA
konijima_gpt_cli-1.1.2.dist-info/WHEEL
konijima_gpt_cli-1.1.2.dist-info/entry_points.txt
konijima_gpt_cli-1.1.2.dist-info/top_level.txt
konijima_gpt_cli-1.1.2.dist-info/RECORD
