Metadata-Version: 2.4
Name: konijima-gpt-cli
Version: 1.1.2
Summary: GPT CLI — A conversational assistant with memory, config, and logging features.
Home-page: https://github.com/Konijima/gpt-cli
Author: Konijima
Author-email: 
License: MIT
Classifier: Programming Language :: Python :: 3
Classifier: Environment :: Console
Classifier: License :: OSI Approved :: MIT License
Classifier: Topic :: Utilities
Requires-Python: >=3.8
License-File: LICENSE
Requires-Dist: openai
Requires-Dist: rich
Requires-Dist: prompt_toolkit
Requires-Dist: python-dotenv
Dynamic: author
Dynamic: classifier
Dynamic: description
Dynamic: description-content-type
Dynamic: home-page
Dynamic: license
Dynamic: license-file
Dynamic: requires-dist
Dynamic: requires-python
Dynamic: summary
